enver/__init__.py
enver/_enver.py
enver-0.2.0.dist-info/LICENSE
enver-0.2.0.dist-info/WHEEL
enver-0.2.0.dist-info/METADATA
enver-0.2.0.dist-info/RECORD
